extended_comm/google/__init__.py
extended_comm/google/gmail.py
extended_comm/google/service.py
extended_comm/google/sheets.py
extended_comm-0.1.2.dist-info/METADATA
extended_comm-0.1.2.dist-info/WHEEL
extended_comm-0.1.2.dist-info/top_level.txt
extended_comm-0.1.2.dist-info/RECORD
